ndx_ibl_metadata/__init__.py
ndx_ibl_metadata/spec/ndx-ibl-metadata.extensions.yaml
ndx_ibl_metadata/spec/ndx-ibl-metadata.namespace.yaml
tests/__init__.py
tests/test_ibl.py
ndx_ibl_metadata-0.1.0.dist-info/LICENSE.txt
ndx_ibl_metadata-0.1.0.dist-info/METADATA
ndx_ibl_metadata-0.1.0.dist-info/WHEEL
ndx_ibl_metadata-0.1.0.dist-info/top_level.txt
ndx_ibl_metadata-0.1.0.dist-info/RECORD
