Metadata-Version: 2.1
Name: ndx-ibl-metadata
Version: 0.1.0
Summary: IBL sessions specific metadata
Home-page: UNKNOWN
Author: Saksham Sharda
Author-email: sxs1790@case.edu
License: BSD 3-Clause
Platform: UNKNOWN
Classifier: Intended Audience :: Developers
Classifier: Intended Audience :: Science/Research
Requires-Dist: pynwb (>=1.3.0)
